abs_auth_rbac_core/__init__.py
abs_auth_rbac_core/auth/__init__.py
abs_auth_rbac_core/auth/auth_functions.py
abs_auth_rbac_core/auth/jwt_functions.py
abs_auth_rbac_core/auth/middleware.py
abs_auth_rbac_core/models/__init__.py
abs_auth_rbac_core/models/base_model.py
abs_auth_rbac_core/models/gov_casbin_rule.py
abs_auth_rbac_core/models/permissions.py
abs_auth_rbac_core/models/rbac_model.py
abs_auth_rbac_core/models/role_permission.py
abs_auth_rbac_core/models/roles.py
abs_auth_rbac_core/models/seeder/permission_seeder.py
abs_auth_rbac_core/models/user.py
abs_auth_rbac_core/models/user_permission.py
abs_auth_rbac_core/models/user_role.py
abs_auth_rbac_core/rbac/__init__.py
abs_auth_rbac_core/rbac/decorator.py
abs_auth_rbac_core/rbac/policy.conf
abs_auth_rbac_core/rbac/service.py
abs_auth_rbac_core/repository/__init__.py
abs_auth_rbac_core/repository/permission_repository.py
abs_auth_rbac_core/repository/role_repository.py
abs_auth_rbac_core/schema/__init__.py
abs_auth_rbac_core/schema/permission.py
abs_auth_rbac_core/service/__init__.py
abs_auth_rbac_core/service/permission_service.py
abs_auth_rbac_core/service/role_service.py
abs_auth_rbac_core/util/__init__.py
abs_auth_rbac_core/util/permission_constants.py
abs_auth_rbac_core-0.3.22.dist-info/METADATA
abs_auth_rbac_core-0.3.22.dist-info/WHEEL
abs_auth_rbac_core-0.3.22.dist-info/RECORD
