Metadata-Version: 2.4
Name: abs-auth-rbac-core
Version: 0.3.22
Summary: RBAC and Auth core utilities including JWT token management.
License-Expression: MIT
Author: AutoBridgeSystems
Author-email: info@autobridgesystems.com
Requires-Python: >=3.11,<4.0
Classifier: Programming Language :: Python :: 3
Classifier: Programming Language :: Python :: 3.11
Classifier: Programming Language :: Python :: 3.12
Classifier: Programming Language :: Python :: 3.13
Classifier: Programming Language :: Python :: 3.14
Requires-Dist: abs-exception-core (>=0.2.2,<0.3.0)
Requires-Dist: abs-nosql-repository-core (>=0.11.8,<0.12.0)
Requires-Dist: abs-repository-core (>=0.3.0,<0.4.0)
Requires-Dist: abs-utils (>=0.4.3,<0.5.0)
Requires-Dist: casbin (>=1.41.0,<2.0.0)
Requires-Dist: casbin-redis-watcher (>=1.3.0,<2.0.0)
Requires-Dist: casbin-sqlalchemy-adapter (>=1.4.0,<2.0.0)
Requires-Dist: fastapi[standard] (>=0.115.2)
Requires-Dist: passlib (>=1.7.4,<2.0.0)
Requires-Dist: psycopg2-binary (>=2.9.10,<3.0.0)
Requires-Dist: pyjwt (>=2.10.1,<3.0.0)
Requires-Dist: sqlalchemy (>=2.0.40,<3.0.0)
